README.md
setup.py
sanic_skin/__init__.py
sanic_skin.egg-info/PKG-INFO
sanic_skin.egg-info/SOURCES.txt
sanic_skin.egg-info/dependency_links.txt
sanic_skin.egg-info/requires.txt
sanic_skin.egg-info/top_level.txt